binr/__init__.py
binr/_modidx.py
binr/bin.py
binr-0.0.2.dist-info/LICENSE
binr-0.0.2.dist-info/METADATA
binr-0.0.2.dist-info/WHEEL
binr-0.0.2.dist-info/entry_points.txt
binr-0.0.2.dist-info/top_level.txt
binr-0.0.2.dist-info/RECORD
