Metadata-Version: 2.1
Name: binr
Version: 0.0.2
Summary: binr
Home-page: https://github.com/dsm-72/binr
Author: dsm-72
Author-email: sumner.magruder@yale.edu
License: Apache Software License 2.0
Keywords: binr bin bins nbins n binner binning bin
Classifier: Development Status :: 4 - Beta
Classifier: Intended Audience :: Developers
Classifier: Natural Language :: English
Classifier: Programming Language :: Python :: 3.11
Classifier: License :: OSI Approved :: Apache Software License
Requires-Python: >=3.11
License-File: LICENSE
Requires-Dist: nchr
Requires-Dist: nlit
Requires-Dist: atyp
Requires-Dist: pstr
Requires-Dist: ston
Provides-Extra: dev
